yspec/__init__.py
yspec/checker.py
yspec/cli.py
yspec-0.1.0.data/scripts/yspec
yspec-0.1.0.dist-info/LICENSE
yspec-0.1.0.dist-info/METADATA
yspec-0.1.0.dist-info/WHEEL
yspec-0.1.0.dist-info/top_level.txt
yspec-0.1.0.dist-info/RECORD
