Metadata-Version: 2.1
Name: yspec
Version: 0.1.0
Summary: YAML structure validator
Home-page: https://github.com/arenadata/yspec
Author: Anton Chevychalov
Author-email: cab@arenadata.io
License: UNKNOWN
Platform: UNKNOWN
Classifier: Programming Language :: Python :: 3
Classifier: License :: OSI Approved :: Apache Software License
Classifier: Operating System :: OS Independent
Requires-Dist: pyyaml
